{
    "metadata": {
        "name": null,
        "url": null
    },
    "codelist-items": {
        "aa": {
            "name": null
        },
        "ab": {
            "name": null
        },
        "ae": {
            "name": null
        },
        "af": {
            "name": null
        },
        "ak": {
            "name": null
        },
        "am": {
            "name": null
        },
        "an": {
            "name": null
        },
        "ar": {
            "name": null
        },
        "as": {
            "name": null
        },
        "av": {
            "name": null
        },
        "ay": {
            "name": null
        },
        "az": {
            "name": null
        },
        "ba": {
            "name": null
        },
        "be": {
            "name": null
        },
        "bg": {
            "name": null
        },
        "bh": {
            "name": null
        },
        "bi": {
            "name": null
        },
        "bm": {
            "name": null
        },
        "bn": {
            "name": null
        },
        "bo": {
            "name": null
        },
        "br": {
            "name": null
        },
        "bs": {
            "name": null
        },
        "ca": {
            "name": null
        },
        "ce": {
            "name": null
        },
        "ch": {
            "name": null
        },
        "co": {
            "name": null
        },
        "cr": {
            "name": null
        },
        "cs": {
            "name": null
        },
        "cu": {
            "name": null
        },
        "cv": {
            "name": null
        },
        "cy": {
            "name": null
        },
        "da": {
            "name": null
        },
        "de": {
            "name": null
        },
        "dv": {
            "name": null
        },
        "dz": {
            "name": null
        },
        "ee": {
            "name": null
        },
        "el": {
            "name": null
        },
        "en": {
            "name": null
        },
        "eo": {
            "name": null
        },
        "es": {
            "name": null
        },
        "et": {
            "name": null
        },
        "eu": {
            "name": null
        },
        "fa": {
            "name": null
        },
        "ff": {
            "name": null
        },
        "fi": {
            "name": null
        },
        "fj": {
            "name": null
        },
        "fo": {
            "name": null
        },
        "fr": {
            "name": null
        },
        "fy": {
            "name": null
        },
        "ga": {
            "name": null
        },
        "gd": {
            "name": null
        },
        "gl": {
            "name": null
        },
        "gn": {
            "name": null
        },
        "gu": {
            "name": null
        },
        "gv": {
            "name": null
        },
        "ha": {
            "name": null
        },
        "he": {
            "name": null
        },
        "hi": {
            "name": null
        },
        "ho": {
            "name": null
        },
        "hr": {
            "name": null
        },
        "ht": {
            "name": null
        },
        "hu": {
            "name": null
        },
        "hy": {
            "name": null
        },
        "hz": {
            "name": null
        },
        "ia": {
            "name": null
        },
        "id": {
            "name": null
        },
        "ie": {
            "name": null
        },
        "ig": {
            "name": null
        },
        "ii": {
            "name": null
        },
        "ik": {
            "name": null
        },
        "io": {
            "name": null
        },
        "is": {
            "name": null
        },
        "it": {
            "name": null
        },
        "iu": {
            "name": null
        },
        "ja": {
            "name": null
        },
        "jv": {
            "name": null
        },
        "ka": {
            "name": null
        },
        "kg": {
            "name": null
        },
        "ki": {
            "name": null
        },
        "kj": {
            "name": null
        },
        "kk": {
            "name": null
        },
        "kl": {
            "name": null
        },
        "km": {
            "name": null
        },
        "kn": {
            "name": null
        },
        "ko": {
            "name": null
        },
        "kr": {
            "name": null
        },
        "ks": {
            "name": null
        },
        "ku": {
            "name": null
        },
        "kv": {
            "name": null
        },
        "kw": {
            "name": null
        },
        "ky": {
            "name": null
        },
        "la": {
            "name": null
        },
        "lb": {
            "name": null
        },
        "lg": {
            "name": null
        },
        "li": {
            "name": null
        },
        "ln": {
            "name": null
        },
        "lo": {
            "name": null
        },
        "lt": {
            "name": null
        },
        "lu": {
            "name": null
        },
        "lv": {
            "name": null
        },
        "mg": {
            "name": null
        },
        "mh": {
            "name": null
        },
        "mi": {
            "name": null
        },
        "mk": {
            "name": null
        },
        "ml": {
            "name": null
        },
        "mn": {
            "name": null
        },
        "mr": {
            "name": null
        },
        "ms": {
            "name": null
        },
        "mt": {
            "name": null
        },
        "my": {
            "name": null
        },
        "na": {
            "name": null
        },
        "nb": {
            "name": null
        },
        "nd": {
            "name": null
        },
        "ne": {
            "name": null
        },
        "ng": {
            "name": null
        },
        "nl": {
            "name": null
        },
        "nn": {
            "name": null
        },
        "no": {
            "name": null
        },
        "nr": {
            "name": null
        },
        "nv": {
            "name": null
        },
        "ny": {
            "name": null
        },
        "oc": {
            "name": null
        },
        "oj": {
            "name": null
        },
        "om": {
            "name": null
        },
        "or": {
            "name": null
        },
        "os": {
            "name": null
        },
        "pa": {
            "name": null
        },
        "pi": {
            "name": null
        },
        "pl": {
            "name": null
        },
        "ps": {
            "name": null
        },
        "pt": {
            "name": null
        },
        "qu": {
            "name": null
        },
        "rm": {
            "name": null
        },
        "rn": {
            "name": null
        },
        "ro": {
            "name": null
        },
        "ru": {
            "name": null
        },
        "rw": {
            "name": null
        },
        "sa": {
            "name": null
        },
        "sc": {
            "name": null
        },
        "sd": {
            "name": null
        },
        "se": {
            "name": null
        },
        "sg": {
            "name": null
        },
        "si": {
            "name": null
        },
        "sk": {
            "name": null
        },
        "sl": {
            "name": null
        },
        "sm": {
            "name": null
        },
        "sn": {
            "name": null
        },
        "so": {
            "name": null
        },
        "sq": {
            "name": null
        },
        "sr": {
            "name": null
        },
        "ss": {
            "name": null
        },
        "st": {
            "name": null
        },
        "su": {
            "name": null
        },
        "sv": {
            "name": null
        },
        "sw": {
            "name": null
        },
        "ta": {
            "name": null
        },
        "te": {
            "name": null
        },
        "tg": {
            "name": null
        },
        "th": {
            "name": null
        },
        "ti": {
            "name": null
        },
        "tk": {
            "name": null
        },
        "tl": {
            "name": null
        },
        "tn": {
            "name": null
        },
        "to": {
            "name": null
        },
        "tr": {
            "name": null
        },
        "ts": {
            "name": null
        },
        "tt": {
            "name": null
        },
        "tw": {
            "name": null
        },
        "ty": {
            "name": null
        },
        "ug": {
            "name": null
        },
        "uk": {
            "name": null
        },
        "ur": {
            "name": null
        },
        "uz": {
            "name": null
        },
        "ve": {
            "name": null
        },
        "vi": {
            "name": null
        },
        "vo": {
            "name": null
        },
        "wa": {
            "name": null
        },
        "wo": {
            "name": null
        },
        "xh": {
            "name": null
        },
        "yi": {
            "name": null
        },
        "yo": {
            "name": null
        },
        "za": {
            "name": null
        },
        "zh": {
            "name": null
        },
        "zu": {
            "name": null
        }
    }
}