{
    "metadata": {
        "name": null
    },
    "codelist-items": {
        "88": {
            "name": "Estados da ex-Iugosl\u00e1via n\u00e3o especificados"
        },
        "89": {
            "name": "Europa, regional"
        },
        "189": {
            "name": "Norte do Saara, regional"
        },
        "289": {
            "name": "Sul do Saara, regional"
        },
        "298": {
            "name": "\u00c1frica, regional"
        },
        "380": {
            "name": "\u00cdndias Ocidentais, regional"
        },
        "389": {
            "name": "Caribe e Am\u00e9rica Central, regional"
        },
        "489": {
            "name": "Am\u00e9rica do Sul, regional"
        },
        "498": {
            "name": "Am\u00e9rica, regional"
        },
        "589": {
            "name": "Oriente M\u00e9dio, regional"
        },
        "619": {
            "name": "\u00c1sia Central, regional"
        },
        "679": {
            "name": "\u00c1sia Meridional, regional"
        },
        "689": {
            "name": "\u00c1sia Meridional e Central, regional"
        },
        "789": {
            "name": "Extremo Oriente, regional"
        },
        "798": {
            "name": "\u00c1sia, regional"
        },
        "889": {
            "name": "Oceania, regional"
        },
        "998": {
            "name": "Pa\u00edses em desenvolvimento, n\u00e3o especificados"
        },
        "1027": {
            "name": "\u00c1frica Oriental, regional"
        },
        "1028": {
            "name": "\u00c1frica Central, regional"
        },
        "1029": {
            "name": "\u00c1frica Austral, regional"
        },
        "1030": {
            "name": "\u00c1frica Ocidental, regional"
        },
        "1031": {
            "name": "Caribe, regional"
        },
        "1032": {
            "name": "Am\u00e9rica Central, regional"
        },
        "1033": {
            "name": "Melan\u00e9sia, regional"
        },
        "1034": {
            "name": "Micron\u00e9sia, regional"
        },
        "1035": {
            "name": "Polin\u00e9sia, regional"
        }
    }
}